src/alu.sv
module alu(
  input logic signed [31:0] A,// Bus de datos de entrada A de 32 bits
  input logic signed [31:0] B,// Bus de datos de entrada B de 32 bits

  input logic [3:0] ALUOp, // Operación a realizar 4 bits

  output logic signed [31:0] ALURes// Resultado de la alu de 32 bits
);

  always_comb begin
    case (ALUOp)
      4'b0000: ALURes = A + B; // Suma
      4'b1000: ALURes = A - B; // Resta
      4'b0001: ALURes = A << B[4:0]; // Desplazamiento lógico a la izquierda
      4'b0010: ALURes = (A < B) ? 32'd1 : 32'd0; // Menor que (set on less than)
      4'b0011: ALURes = ($unsigned(A) < $unsigned(B)) ? 32'd1 : 32'd0; // Menor que sin signo
      4'b0100: ALURes = A ^ B; // XOR
      4'b0101: ALURes = A >> B[4:0]; // Desplazamiento lógico a la derecha
      4'b1101: ALURes = A >>> B[4:0]; // Desplazamiento aritmético a la derecha
      4'b0110: ALURes = A | B; // OR
      4'b0111: ALURes = A & B; // AND
      4'b1001: ALURes = B; // Pass B (para instrucciones como LUI)
      default: ALURes = 32'd0; // Valor por defecto
    endcase
  end

endmodule

tb/alu_tb.sv
`timescale 1ns/1ps

module alu_tb;

  logic signed [31:0] A, B;
  logic [3:0] ALUOp;
  logic signed [31:0] ALURes;

  alu uut (
    .A(A), .B(B), .ALUOp(ALUOp), .ALURes(ALURes)
  );

  initial begin
    $dumpfile("alu.vcd");  // Archivo de salida para la forma de onda
    $dumpvars(0, alu_tb);  // Guarda todas las señales

    $display("=== INICIO DE SIMULACIÓN ===");

    // Suma
    A = 32'd10; B = 32'd5; ALUOp = 4'b0000; #10;
    $display("ADD: %d + %d = %d", A, B, ALURes);

    // Resta
    A = 32'd10; B = 32'd20; ALUOp = 4'b1000; #10;
    $display("SUB: %d - %d = %d", A, B, ALURes);

    // Shift lógico izquierda
    A = 32'd3; B = 32'd2; ALUOp = 4'b0001; #10;
    $display("SLL: %d << %d = %d", A, B, ALURes);

    // Menor que (signed)
    A = -5; B = 3; ALUOp = 4'b0010; #10;
    $display("SLT: %d < %d = %d", A, B, ALURes);

    // Menor que (unsigned)
    A = -5; B = 3; ALUOp = 4'b0011; #10;
    $display("SLTU: %d < %d = %d", A, B, ALURes);

    // XOR
    A = 32'hF0F0F0F0; B = 32'h0F0F0F0F; ALUOp = 4'b0100; #10;
    $display("XOR: %h ^ %h = %h", A, B, ALURes);

    // Shift aritmético derecha
    A = -32'd64; B = 32'd3; ALUOp = 4'b1101; #10;
    $display("SRA: %d >>> %d = %d", A, B, ALURes);

    // OR
    A = 32'hAAAA0000; B = 32'h0000BBBB; ALUOp = 4'b0110; #10;
    $display("OR: %h | %h = %h", A, B, ALURes);

    // AND
    A = 32'hFFFF0000; B = 32'h00FF00FF; ALUOp = 4'b0111; #10;
    $display("AND: %h & %h = %h", A, B, ALURes);

    // Pasar B
    A = 32'h12345678; B = 32'h87654321; ALUOp = 4'b1001; #10;
    $display("PASS B: %h", ALURes);

    $display("=== FIN DE SIMULACIÓN ===");
    #10 $finish;
  end

endmodule

vcd/alu_tb.vcd
$date
	Thu Oct 30 17:04:07 2025
$end
$version
	Icarus Verilog
$end
$timescale
	1ps
$end
$scope module alu_tb $end
$var wire 32 ! ALURes [31:0] $end
$var reg 32 " A [31:0] $end
$var reg 4 # ALUOp [3:0] $end
$var reg 32 $ B [31:0] $end
$scope module uut $end
$var wire 32 % A [31:0] $end
$var wire 4 & ALUOp [3:0] $end
$var wire 32 ' B [31:0] $end
$var reg 32 ( ALURes [31:0] $end
$upscope $end
$upscope $end
$enddefinitions $end
$comment Show the parameter values. $end
$dumpall
$end
#0
$dumpvars
b1111 (
b101 '
b0 &
b1010 %
b101 $
b0 #
b1010 "
b1111 !
$end
#10000
b11111111111111111111111111110110 !
b11111111111111111111111111110110 (
b1000 #
b1000 &
b10100 $
b10100 '
#20000
b1100 !
b1100 (
b1 #
b1 &
b10 $
b10 '
b11 "
b11 %
#30000
b1 !
b1 (
b10 #
b10 &
b11 $
b11 '
b11111111111111111111111111111011 "
b11111111111111111111111111111011 %
#40000
b0 !
b0 (
b11 #
b11 &
#50000
b11111111111111111111111111111111 !
b11111111111111111111111111111111 (
b100 #
b100 &
b1111000011110000111100001111 $
b1111000011110000111100001111 '
b11110000111100001111000011110000 "
b11110000111100001111000011110000 %
#60000
b11111111111111111111111111111000 !
b11111111111111111111111111111000 (
b1101 #
b1101 &
b11 $
b11 '
b11111111111111111111111111000000 "
b11111111111111111111111111000000 %
#70000
b10101010101010101011101110111011 !
b10101010101010101011101110111011 (
b110 #
b110 &
b1011101110111011 $
b1011101110111011 '
b10101010101010100000000000000000 "
b10101010101010100000000000000000 %
#80000
b111111110000000000000000 !
b111111110000000000000000 (
b111 #
b111 &
b111111110000000011111111 $
b111111110000000011111111 '
b11111111111111110000000000000000 "
b11111111111111110000000000000000 %
#90000
b10000111011001010100001100100001 !
b10000111011001010100001100100001 (
b1001 #
b1001 &
b10000111011001010100001100100001 $
b10000111011001010100001100100001 '
b10010001101000101011001111000 "
b10010001101000101011001111000 %
