src/clock_divider.sv
// ============================================================================
// Clock Divider Module
// ============================================================================
// Divide el clock de 50MHz para generar clocks más lentos
// Usado para el modo automático de ejecución
// ============================================================================

module clock_divider #(
    parameter DIVIDER = 25_000_000  // Default: 1Hz desde 50MHz
)(
    input  logic clk_in,
    input  logic rst,
    output logic clk_out
);

    logic [31:0] counter;

    always_ff @(posedge clk_in or posedge rst) begin
        if (rst) begin
            counter <= 32'd0;
            clk_out <= 1'b0;
        end else begin
            if (counter >= DIVIDER - 1) begin
                counter <= 32'd0;
                clk_out <= ~clk_out;
            end else begin
                counter <= counter + 32'd1;
            end
        end
    end

endmodule

tb/clock_divider_tb.sv
// ============================================================================
// Clock Divider Testbench
// ============================================================================

`timescale 1ns/1ps

module clock_divider_tb;

    logic clk_in;
    logic rst;
    logic clk_out;

    // Instancia del DUT
    clock_divider #(
        .DIVIDER(10)  // Dividir por 10 para simulación
    ) dut (
        .clk_in(clk_in),
        .rst(rst),
        .clk_out(clk_out)
    );

    // Generador de clock de entrada (50 MHz = 20ns)
    initial begin
        clk_in = 0;
        forever #10 clk_in = ~clk_in;
    end

    // Estímulos
    initial begin
        $dumpfile("vcd/clock_divider_tb.vcd");
        $dumpvars(0, clock_divider_tb);

        // Reset
        rst = 1;
        #50;
        rst = 0;

        // Dejar correr por varios ciclos
        #2000;

        $display("=== Test completado ===");
        $display("Clock de entrada: 50MHz");
        $display("Clock de salida esperado: 5MHz (DIVIDER=10)");
        $finish;
    end

    // Monitor para verificar la frecuencia
    integer edge_count;
    real start_time, end_time, frequency;

    initial begin
        edge_count = 0;
        start_time = 0;
        @(negedge rst);
        start_time = $realtime;
        
        repeat(10) @(posedge clk_out) begin
            edge_count = edge_count + 1;
        end
        
        end_time = $realtime;
        frequency = edge_count / ((end_time - start_time) / 1e9);
        $display("Frecuencia medida: %f MHz", frequency / 1e6);
    end

endmodule

vcd/clock_divider_tb.vcd
$date
	Wed Nov 19 17:38:55 2025
$end
$version
	Icarus Verilog
$end
$timescale
	1ps
$end
$scope module clock_divider_tb $end
$var wire 1 ! clk_out $end
$var reg 1 " clk_in $end
$var reg 1 # rst $end
$var integer 32 $ edge_count [31:0] $end
$var real 1 % end_time $end
$var real 1 & frequency $end
$var real 1 ' start_time $end
$scope module dut $end
$var wire 1 " clk_in $end
$var wire 1 # rst $end
$var parameter 32 ( DIVIDER $end
$var reg 1 ! clk_out $end
$var reg 32 ) counter [31:0] $end
$upscope $end
$upscope $end
$enddefinitions $end
$comment Show the parameter values. $end
$dumpall
b1010 (
$end
#0
$dumpvars
b0 )
r0 '
r0 &
r0 %
b0 $
1#
0"
0!
$end
#10000
1"
#20000
0"
#30000
1"
#40000
0"
#50000
b1 )
r50 '
1"
0#
#60000
0"
#70000
b10 )
1"
#80000
0"
#90000
b11 )
1"
#100000
0"
#110000
b100 )
1"
#120000
0"
#130000
b101 )
1"
#140000
0"
#150000
b110 )
1"
#160000
0"
#170000
b111 )
1"
#180000
0"
#190000
b1000 )
1"
#200000
0"
#210000
b1001 )
1"
#220000
0"
#230000
b1 $
1!
b0 )
1"
#240000
0"
#250000
b1 )
1"
#260000
0"
#270000
b10 )
1"
#280000
0"
#290000
b11 )
1"
#300000
0"
#310000
b100 )
1"
#320000
0"
#330000
b101 )
1"
#340000
0"
#350000
b110 )
1"
#360000
0"
#370000
b111 )
1"
#380000
0"
#390000
b1000 )
1"
#400000
0"
#410000
b1001 )
1"
#420000
0"
#430000
0!
b0 )
1"
#440000
0"
#450000
b1 )
1"
#460000
0"
#470000
b10 )
1"
#480000
0"
#490000
b11 )
1"
#500000
0"
#510000
b100 )
1"
#520000
0"
#530000
b101 )
1"
#540000
0"
#550000
b110 )
1"
#560000
0"
#570000
b111 )
1"
#580000
0"
#590000
b1000 )
1"
#600000
0"
#610000
b1001 )
1"
#620000
0"
#630000
b10 $
1!
b0 )
1"
#640000
0"
#650000
b1 )
1"
#660000
0"
#670000
b10 )
1"
#680000
0"
#690000
b11 )
1"
#700000
0"
#710000
b100 )
1"
#720000
0"
#730000
b101 )
1"
#740000
0"
#750000
b110 )
1"
#760000
0"
#770000
b111 )
1"
#780000
0"
#790000
b1000 )
1"
#800000
0"
#810000
b1001 )
1"
#820000
0"
#830000
0!
b0 )
1"
#840000
0"
#850000
b1 )
1"
#860000
0"
#870000
b10 )
1"
#880000
0"
#890000
b11 )
1"
#900000
0"
#910000
b100 )
1"
#920000
0"
#930000
b101 )
1"
#940000
0"
#950000
b110 )
1"
#960000
0"
#970000
b111 )
1"
#980000
0"
#990000
b1000 )
1"
#1000000
0"
#1010000
b1001 )
1"
#1020000
0"
#1030000
b11 $
1!
b0 )
1"
#1040000
0"
#1050000
b1 )
1"
#1060000
0"
#1070000
b10 )
1"
#1080000
0"
#1090000
b11 )
1"
#1100000
0"
#1110000
b100 )
1"
#1120000
0"
#1130000
b101 )
1"
#1140000
0"
#1150000
b110 )
1"
#1160000
0"
#1170000
b111 )
1"
#1180000
0"
#1190000
b1000 )
1"
#1200000
0"
#1210000
b1001 )
1"
#1220000
0"
#1230000
0!
b0 )
1"
#1240000
0"
#1250000
b1 )
1"
#1260000
0"
#1270000
b10 )
1"
#1280000
0"
#1290000
b11 )
1"
#1300000
0"
#1310000
b100 )
1"
#1320000
0"
#1330000
b101 )
1"
#1340000
0"
#1350000
b110 )
1"
#1360000
0"
#1370000
b111 )
1"
#1380000
0"
#1390000
b1000 )
1"
#1400000
0"
#1410000
b1001 )
1"
#1420000
0"
#1430000
b100 $
1!
b0 )
1"
#1440000
0"
#1450000
b1 )
1"
#1460000
0"
#1470000
b10 )
1"
#1480000
0"
#1490000
b11 )
1"
#1500000
0"
#1510000
b100 )
1"
#1520000
0"
#1530000
b101 )
1"
#1540000
0"
#1550000
b110 )
1"
#1560000
0"
#1570000
b111 )
1"
#1580000
0"
#1590000
b1000 )
1"
#1600000
0"
#1610000
b1001 )
1"
#1620000
0"
#1630000
0!
b0 )
1"
#1640000
0"
#1650000
b1 )
1"
#1660000
0"
#1670000
b10 )
1"
#1680000
0"
#1690000
b11 )
1"
#1700000
0"
#1710000
b100 )
1"
#1720000
0"
#1730000
b101 )
1"
#1740000
0"
#1750000
b110 )
1"
#1760000
0"
#1770000
b111 )
1"
#1780000
0"
#1790000
b1000 )
1"
#1800000
0"
#1810000
b1001 )
1"
#1820000
0"
#1830000
b101 $
1!
b0 )
1"
#1840000
0"
#1850000
b1 )
1"
#1860000
0"
#1870000
b10 )
1"
#1880000
0"
#1890000
b11 )
1"
#1900000
0"
#1910000
b100 )
1"
#1920000
0"
#1930000
b101 )
1"
#1940000
0"
#1950000
b110 )
1"
#1960000
0"
#1970000
b111 )
1"
#1980000
0"
#1990000
b1000 )
1"
#2000000
0"
#2010000
b1001 )
1"
#2020000
0"
#2030000
0!
b0 )
1"
#2040000
0"
#2050000
b1 )
1"
