src/pc.sv
//Program Counter (PC)

module pc(
  input logic clk, // Reloj del sistema
  input logic reset, // Señal de reinicio
  input logic [31:0] next_pc, // Dirección de la siguiente instrucción
  output logic [31:0] pc_out // Dirección actual del PC
);

  always_ff @(posedge clk or posedge reset) begin
    if (reset) begin
      pc_out <= 32'b0; // Reiniciar el PC a 0
    end else begin
      pc_out <= next_pc; // Actualizar el PC con la siguiente dirección
    end
  end
endmodule

tb/pc_tb.sv
//Program counter testbench

`timescale 1ns/1ps

module pc_tb;

  logic clk;
  logic reset;
  logic [31:0] next_pc;
  logic [31:0] pc_out;

  // Instancia del módulo PC
  pc uut (
    .clk(clk),
    .reset(reset),
    .next_pc(next_pc),
    .pc_out(pc_out)
  );

  // Generador de reloj: periodo 10 ns (100 MHz)
  always #5 clk = ~clk;

  initial begin
    // Inicialización
    $dumpfile("vcd/pc.vcd");
    $dumpvars(0, pc_tb);
    $display("=== INICIO DE SIMULACIÓN ===");

    clk = 0;
    reset = 1;     // Activa reset
    next_pc = 32'h00000000;

    #10;           // Espera un ciclo
    reset = 0;     // Desactiva reset

    // Prueba 1: cargar 0x00000004
    next_pc = 32'h00000004;
    #10;
    $display("PC debe ser 0x00000004: %h", pc_out);

    // Prueba 2: cargar 0x00000008
    next_pc = 32'h00000008;
    #10;
    $display("PC debe ser 0x00000008: %h", pc_out);

    // Prueba 3: cargar 0x0000000C
    next_pc = 32'h0000000C;
    #10;
    $display("PC debe ser 0x0000000C: %h", pc_out);

    // Prueba 4: aplicar reset
    reset = 1;
    #10;
    $display("Después de reset, PC debe ser 0: %h", pc_out);
    reset = 0;

    // Prueba 5: cargar nuevo valor después de reset
    next_pc = 32'h00000020;
    #10;
    $display("PC debe ser 0x00000020: %h", pc_out);

    $display("=== FIN DE SIMULACIÓN ===");
    #10 $finish;
  end

endmodule

vcd/pc.vcd
$date
	Thu Oct 30 17:03:05 2025
$end
$version
	Icarus Verilog
$end
$timescale
	1ps
$end
$scope module pc_tb $end
$var wire 32 ! pc_out [31:0] $end
$var reg 1 " clk $end
$var reg 32 # next_pc [31:0] $end
$var reg 1 $ reset $end
$scope module uut $end
$var wire 1 " clk $end
$var wire 32 % next_pc [31:0] $end
$var wire 1 $ reset $end
$var reg 32 & pc_out [31:0] $end
$upscope $end
$upscope $end
$enddefinitions $end
$comment Show the parameter values. $end
$dumpall
$end
#0
$dumpvars
b0 &
b0 %
1$
b0 #
0"
b0 !
$end
#5000
1"
#10000
0"
b100 #
b100 %
0$
#15000
b100 !
b100 &
1"
#20000
0"
b1000 #
b1000 %
#25000
b1000 !
b1000 &
1"
#30000
0"
b1100 #
b1100 %
#35000
b1100 !
b1100 &
1"
#40000
b0 !
b0 &
0"
1$
#45000
1"
#50000
0"
b100000 #
b100000 %
0$
#55000
b100000 !
b100000 &
1"
